netshow_core_lib-1.1.3-py2.7-nspkg.pth
netshowlib/_version.py
netshowlib/netshowlib.py
netshowlib/lsb_release.py
netshow_core_lib-1.1.3.dist-info/METADATA
netshow_core_lib-1.1.3.dist-info/RECORD
netshow_core_lib-1.1.3.dist-info/metadata.json
netshow_core_lib-1.1.3.dist-info/WHEEL
netshow_core_lib-1.1.3.dist-info/DESCRIPTION.rst
netshow_core_lib-1.1.3.dist-info/namespace_packages.txt
netshow_core_lib-1.1.3.dist-info/top_level.txt
