Metadata-Version: 2.0
Name: netshow-core-lib
Version: 1.1.3
Summary: Netshow Core Library. Provides high level user API for netshow providers
Home-page: http://github.com/CumulusNetworks/netshow-core
Author: Cumulus Networks
Author-email: ce-ceng@cumulusnetworks.com
License: GPLv2
Platform: UNKNOWN
Classifier: Development Status :: 4 - Beta
Classifier: Topic :: System :: Networking
Classifier: Intended Audience :: Developers
Classifier: Intended Audience :: System Administrators
Classifier: Operating System :: POSIX :: Linux
